junebug/__init__.py
junebug/amqp.py
junebug/api.py
junebug/channel.py
junebug/command_line.py
junebug/config.py
junebug/error.py
junebug/logging_service.py
junebug/plugin.py
junebug/rabbitmq.py
junebug/service.py
junebug/stores.py
junebug/utils.py
junebug/validate.py
junebug/workers.py
junebug/plugins/__init__.py
junebug/plugins/nginx/__init__.py
junebug/plugins/nginx/location.template
junebug/plugins/nginx/plugin.py
junebug/plugins/nginx/vhost.template
junebug/plugins/nginx/tests/__init__.py
junebug/plugins/nginx/tests/test_plugin.py
junebug/router/__init__.py
junebug/router/base.py
junebug/router/from_address.py
junebug/tests/__init__.py
junebug/tests/helpers.py
junebug/tests/test_amqp.py
junebug/tests/test_api.py
junebug/tests/test_channel.py
junebug/tests/test_command_line.py
junebug/tests/test_from_address_router.py
junebug/tests/test_logging_service.py
junebug/tests/test_plugin.py
junebug/tests/test_rabbitmq.py
junebug/tests/test_router.py
junebug/tests/test_service.py
junebug/tests/test_stores.py
junebug/tests/test_utils.py
junebug/tests/test_validate.py
junebug/tests/test_workers.py
junebug/tests/utils.py
junebug-0.2.0.dist-info/LICENSE
junebug-0.2.0.dist-info/METADATA
junebug-0.2.0.dist-info/WHEEL
junebug-0.2.0.dist-info/entry_points.txt
junebug-0.2.0.dist-info/top_level.txt
junebug-0.2.0.dist-info/RECORD
