Metadata-Version: 2.1
Name: junebug
Version: 0.2.0
Summary: A system for managing text messaging transports via a RESTful HTTP interface
Home-page: http://github.com/praekelt/junebug
Author: Praekelt Foundation
Author-email: dev@praekeltfoundation.org
License: BSD
Platform: UNKNOWN
Classifier: Development Status :: 4 - Beta
Classifier: Intended Audience :: Developers
Classifier: License :: OSI Approved :: BSD License
Classifier: Operating System :: POSIX
Classifier: Programming Language :: Python
Classifier: Topic :: Software Development :: Libraries :: Python Modules
Classifier: Topic :: Internet :: WWW/HTTP
Requires-Dist: pyasn1
Requires-Dist: klein (<=17.10.0)
Requires-Dist: jsonschema
Requires-Dist: treq (<20.4.1)
Requires-Dist: Twisted (<21.0.0,>=20.3.0)
Requires-Dist: vumi (>=0.6.19)
Requires-Dist: confmodel
Requires-Dist: PyYAML
Requires-Dist: raven (<7.0.0,>=6.0.0)
